colablib/__init__.py
colablib/colored_print.py
colablib/sd_models/__init__.py
colablib/sd_models/downloader.py
colablib/sd_models/validators.py
colablib/utils/__init__.py
colablib/utils/git_utils.py
colablib/utils/py_utils.py
colablib/utils/ubuntu_utils.py
colablib-0.1.7.dist-info/METADATA
colablib-0.1.7.dist-info/WHEEL
colablib-0.1.7.dist-info/top_level.txt
colablib-0.1.7.dist-info/RECORD
